asg/__init__.py
asg/__main__.py
asg/entities.py
asg/intermediate_lang.py
asg/main.py
asg/generation/__init__.py
asg/generation/constraints.py
asg/grammar/__init__.py
asg/input/__init__.py
asg/input/spice/__init__.py
asg/input/spice/spice.lark
asg/library_source/__init__.py
asg/library_source/kicad_symbol_lib/__init__.py
asg/library_source/kicad_symbol_lib/s_expression.lark
asg/library_source/xschem/__init__.py
asg/library_source/xschem/xschem.lark
asg/output/__init__.py
asg/output/eeschema/__init__.py
asg/output/json/__init__.py
asg/output/text/__init__.py
asg/output/xcircuit_ps/__init__.py
asg/output/xschem/__init__.py
asg-1.1.0.dist-info/LICENSE
asg-1.1.0.dist-info/METADATA
asg-1.1.0.dist-info/WHEEL
asg-1.1.0.dist-info/entry_points.txt
asg-1.1.0.dist-info/top_level.txt
asg-1.1.0.dist-info/RECORD
