Metadata-Version: 2.1
Name: asg
Version: 1.1.0
Summary: A tool to automatically generate schematics from SPICE netlists
Home-page: https://github.com/aidangoettsch/asg
Author: Aidan Goettsch
License: UNKNOWN
Platform: UNKNOWN
Classifier: Programming Language :: Python :: 3
Classifier: License :: OSI Approved :: MIT License
Classifier: Operating System :: OS Independent
Requires-Python: >=3.6
